[{"Rank": 1, "Rank (Prev)": 1, "Code": "NoCode 1", "Name": "ฐิตภัทร ปรีชาญาณ", "Birth Year": 2553, "Team": "ไทยรุ่ง", "Age": 16, "NEW POINT JAN 26": 3188.75, "Chonburi PAO 2026": 0.0, "Yasothon Open 2026": 0.0, "Total Point": 3188.75}, {"Rank": 2, "Rank (Prev)": 2, "Code": "TH09972", "Name": "สราวุธ สังขรัตน์", "Birth Year": 2552, "Team": "สโมสรกีฬาเซ็นทรัล", "Age": 17, "NEW POINT JAN 26": 2472.2, "Chonburi PAO 2026": 178.4, "Yasothon Open 2026": 0.0, "Total Point": 2650.6}, {"Rank": 3, "Rank (Prev)": 3, "Code": "TH18910", "Name": "กันตณัฐ เพ็ชรสันทัด", "Birth Year": 2553, "Team": "สโมสรกีฬาเซ็นทรัล", "Age": 16, "NEW POINT JAN 26": 2375.75, "Chonburi PAO 2026": 250.4, "Yasothon Open 2026": 0.0, "Total Point": 2626.15}, {"Rank": 4, "Rank (Prev)": 4, "Code": "TH19507", "Name": "อภิภูมิ ลักษณา", "Birth Year": 2552, "Team": "ไทยรุ่ง", "Age": 17, "NEW POINT JAN 26": 1938.6, "Chonburi PAO 2026": 92.0, "Yasothon Open 2026": 0.0, "Total Point": 2030.6}, {"Rank": 5, "Rank (Prev)": 5, "Code": "TH18418", "Name": "ธนภัทร หน่อแก้ว", "Birth Year": 2553, "Team": "สโมสรเทเบิลเทนนิสตำรวจ", "Age": 16, "NEW POINT JAN 26": 1733.15, "Chonburi PAO 2026": 0.0, "Yasothon Open 2026": 0.0, "Total Point": 1733.15}, {"Rank": 6, "Rank (Prev)": 6, "Code": "NoCode 60", "Name": "นิมิตร สร้อยพวง", "Birth Year": 2553, "Team": "สโมสรเทเบิลเทนนิสตำรวจ", "Age": 16, "NEW POINT JAN 26": 1568.0, "Chonburi PAO 2026": 0.0, "Yasothon Open 2026": 0.0, "Total Point": 1568.0}, {"Rank": 7, "Rank (Prev)": 7, "Code": "TH19651", "Name": "ไซกุน ธนไชยรุ่ง", "Birth Year": 2552, "Team": "สโมสรกีฬาเซ็นทรัล", "Age": 17, "NEW POINT JAN 26": 1355.8, "Chonburi PAO 2026": 202.4, "Yasothon Open 2026": 0.0, "Total Point": 1558.2}, {"Rank": 8, "Rank (Prev)": 9, "Code": "TH18567", "Name": "อภิศักดิ์ ภูมิพันธ์", "Birth Year": 2553, "Team": "สโมสรเทเบิลเทนนิสตำรวจ", "Age": 16, "NEW POINT JAN 26": 1277.2, "Chonburi PAO 2026": 135.2, "Yasothon Open 2026": 0.0, "Total Point": 1412.4}, {"Rank": 9, "Rank (Prev)": 8, "Code": "TH19942", "Name": "ณัฐชนน เตปินใจ", "Birth Year": 2552, "Team": "สโมสรกีฬาเซ็นทรัล", "Age": 17, "NEW POINT JAN 26": 1312.6, "Chonburi PAO 2026": 92.0, "Yasothon Open 2026": 0.0, "Total Point": 1404.6}, {"Rank": 10, "Rank (Prev)": 11, "Code": "TH09975", "Name": "ทชภณ ช่างประดิษฐ์", "Birth Year": 2553, "Team": "สโมสรกีฬาเซ็นทรัล", "Age": 16, "NEW POINT JAN 26": 1168.5, "Chonburi PAO 2026": 63.2, "Yasothon Open 2026": 0.0, "Total Point": 1231.7}, {"Rank": 11, "Rank (Prev)": 12, "Code": "TH09969", "Name": "ณภพ ดรณีรัตน์", "Birth Year": 2554, "Team": "สโมสรกีฬาเซ็นทรัล", "Age": 15, "NEW POINT JAN 26": 1066.2, "Chonburi PAO 2026": 135.2, "Yasothon Open 2026": 0.0, "Total Point": 1201.4}, {"Rank": 12, "Rank (Prev)": 10, "Code": "NoCode 74", "Name": "ธรรมวิทย์ ตั้งธนวัฒน์", "Birth Year": 2552, "Team": "สโมสรเทเบิลเทนนิสบ้านปู", "Age": 17, "NEW POINT JAN 26": 1179.0, "Chonburi PAO 2026": 0.0, "Yasothon Open 2026": 0.0, "Total Point": 1179.0}, {"Rank": 13, "Rank (Prev)": 13, "Code": "TH18535", "Name": "ธนกฤต อึ้งมณีประเสริฐ", "Birth Year": 2553, "Team": "สโมสรเทเบิลเทนนิสบ้านปู", "Age": 16, "NEW POINT JAN 26": 1038.05, "Chonburi PAO 2026": 135.2, "Yasothon Open 2026": 0.0, "Total Point": 1173.25}, {"Rank": 14, "Rank (Prev)": 14, "Code": "TH20137", "Name": "ภูมิภัทร น้อยทา", "Birth Year": 2555, "Team": "สโมสรกีฬาเซ็นทรัล", "Age": 14, "NEW POINT JAN 26": 827.0, "Chonburi PAO 2026": 332.0, "Yasothon Open 2026": 0.0, "Total Point": 1159.0}, {"Rank": 15, "Rank (Prev)": 15, "Code": "TH20404", "Name": "ชัชวัช อรุณเลิศวิทยา", "Birth Year": 2552, "Team": "แต้จิ๋วสุราษฎร์ธานี", "Age": 17, "NEW POINT JAN 26": 800.84, "Chonburi PAO 2026": 63.2, "Yasothon Open 2026": 0.0, "Total Point": 864.04}, {"Rank": 16, "Rank (Prev)": 17, "Code": "TH18088", "Name": "ชนาเมธ สีเลี้ยง", "Birth Year": 2554, "Team": "สโมสรเทเบิลเทนนิสตำรวจ", "Age": 15, "NEW POINT JAN 26": 664.3, "Chonburi PAO 2026": 92.0, "Yasothon Open 2026": 0.0, "Total Point": 756.3}, {"Rank": 17, "Rank (Prev)": 18, "Code": "TH18101", "Name": "นรากรณ์ บุญกาญจน์", "Birth Year": 2552, "Team": "โรงเรียนกีฬากรุงเทพ", "Age": 17, "NEW POINT JAN 26": 597.84, "Chonburi PAO 2026": 63.2, "Yasothon Open 2026": 80.0, "Total Point": 741.04}, {"Rank": 18, "Rank (Prev)": 16, "Code": "TH19209", "Name": "ถิรคุณ จันทร์วิทัน", "Birth Year": 2552, "Team": "KUS", "Age": 17, "NEW POINT JAN 26": 670.75, "Chonburi PAO 2026": 63.2, "Yasothon Open 2026": 0.0, "Total Point": 733.95}, {"Rank": 19, "Rank (Prev)": 19, "Code": "TH20191", "Name": "ณัติวัชร์ ไกรสิทธิรัศม์", "Birth Year": 2553, "Team": "สโมสรกีฬาเซ็นทรัล", "Age": 16, "NEW POINT JAN 26": 581.15, "Chonburi PAO 2026": 63.2, "Yasothon Open 2026": 0.0, "Total Point": 644.35}, {"Rank": 20, "Rank (Prev)": 20, "Code": "TH19992", "Name": "นพภัสสร ศรันย์บัณฑิต", "Birth Year": 2552, "Team": "สโมสรเทเบิลเทนนิสตำรวจ", "Age": 17, "NEW POINT JAN 26": 565.79, "Chonburi PAO 2026": 63.2, "Yasothon Open 2026": 0.0, "Total Point": 628.99}, {"Rank": 21, "Rank (Prev)": 21, "Code": "TH19082", "Name": "ปุณณกฤษฏิ์ ชัยสุนทรโยธิน", "Birth Year": 2553, "Team": "สโมสรกีฬาเซ็นทรัล", "Age": 16, "NEW POINT JAN 26": 533.0, "Chonburi PAO 2026": 63.2, "Yasothon Open 2026": 0.0, "Total Point": 596.2}, {"Rank": 22, "Rank (Prev)": 22, "Code": "TH19350", "Name": "ภัทรดนัย ดนัยพิทักษ์", "Birth Year": 2552, "Team": "เมืองทอง", "Age": 17, "NEW POINT JAN 26": 503.2, "Chonburi PAO 2026": 20.0, "Yasothon Open 2026": 0.0, "Total Point": 523.2}, {"Rank": 23, "Rank (Prev)": 25, "Code": "TH18267", "Name": "ปวริศร์ ทองหล่อ", "Birth Year": 2555, "Team": "สโมสรกีฬาเซ็นทรัล", "Age": 14, "NEW POINT JAN 26": 323.0, "Chonburi PAO 2026": 92.0, "Yasothon Open 2026": 0.0, "Total Point": 415.0}, {"Rank": 24, "Rank (Prev)": 23, "Code": "TH19814", "Name": "ทอฟ้าใหม่ อิ่มละมัย", "Birth Year": 2552, "Team": "ไทยรุ่ง", "Age": 17, "NEW POINT JAN 26": 420.4, "Chonburi PAO 2026": -20.0, "Yasothon Open 2026": 0.0, "Total Point": 400.4}, {"Rank": 25, "Rank (Prev)": 27, "Code": "TH19569", "Name": "ไกรวัฒน์ ไกรสิทธิรัศม์", "Birth Year": 2554, "Team": "สโมสรกีฬาเซ็นทรัล", "Age": 15, "NEW POINT JAN 26": 299.2, "Chonburi PAO 2026": 92.0, "Yasothon Open 2026": 0.0, "Total Point": 391.2}, {"Rank": 26, "Rank (Prev)": 24, "Code": "NoCode 110", "Name": "Phongsavanh Sengmany", "Birth Year": 2553, "Team": "WAGA SPORT", "Age": 16, "NEW POINT JAN 26": 332.7, "Chonburi PAO 2026": 0.0, "Yasothon Open 2026": 0.0, "Total Point": 332.7}, {"Rank": 27, "Rank (Prev)": 26, "Code": "NoCode 119", "Name": "พัทธพล แย้มลีมูล", "Birth Year": 2553, "Team": "NCN TABLE TENNIS", "Age": 16, "NEW POINT JAN 26": 307.8, "Chonburi PAO 2026": 0.0, "Yasothon Open 2026": 0.0, "Total Point": 307.8}, {"Rank": 28, "Rank (Prev)": 28, "Code": "NoCode 2", "Name": "จักรพันธ์ ทองคำ", "Birth Year": 2553, "Team": "แต้จิ๋วสุราษฎร์ธานี", "Age": 16, "NEW POINT JAN 26": 293.9, "Chonburi PAO 2026": 0.0, "Yasothon Open 2026": 0.0, "Total Point": 293.9}, {"Rank": 29, "Rank (Prev)": 34, "Code": "TH20054", "Name": "พัสสกรณ์ อรุณอาศิรกุล", "Birth Year": 2552, "Team": "สโมสรเทเบิลเทนนิสพิษณุโลก", "Age": 17, "NEW POINT JAN 26": 177.1, "Chonburi PAO 2026": 63.2, "Yasothon Open 2026": 32.0, "Total Point": 272.3}, {"Rank": 30, "Rank (Prev)": 32, "Code": "TH19528", "Name": "พัฒน์ มานัสสถิตย์", "Birth Year": 2554, "Team": "ไทยรุ่ง", "Age": 15, "NEW POINT JAN 26": 192.6, "Chonburi PAO 2026": 63.2, "Yasothon Open 2026": 0.0, "Total Point": 255.8}, {"Rank": 31, "Rank (Prev)": 33, "Code": "TH19093", "Name": "ภูมิพัฒน์ วงค์ขัน", "Birth Year": 2553, "Team": "สโมสรเทเบิลเทนนิสบ้านปู", "Age": 16, "NEW POINT JAN 26": 187.6, "Chonburi PAO 2026": 63.2, "Yasothon Open 2026": 0.0, "Total Point": 250.8}, {"Rank": 32, "Rank (Prev)": 29, "Code": "NoCode 12", "Name": "Leonard Piyachai", "Birth Year": 2553, "Team": "สโมสรเทเบิลเทนนิสบ้านปู", "Age": 16, "NEW POINT JAN 26": 250.0, "Chonburi PAO 2026": 0.0, "Yasothon Open 2026": 0.0, "Total Point": 250.0}, {"Rank": 33, "Rank (Prev)": 40, "Code": "TH20047", "Name": "ธนรัตน์ เสียงสูง", "Birth Year": 2554, "Team": "ไทยรุ่ง", "Age": 15, "NEW POINT JAN 26": 143.4, "Chonburi PAO 2026": 92.0, "Yasothon Open 2026": 0.0, "Total Point": 235.4}, {"Rank": 34, "Rank (Prev)": 31, "Code": "TH19488", "Name": "ธนโชติ อ่อนศรี", "Birth Year": 2554, "Team": "Pin Academy", "Age": 15, "NEW POINT JAN 26": 206.0, "Chonburi PAO 2026": 20.0, "Yasothon Open 2026": 0.0, "Total Point": 226.0}, {"Rank": 35, "Rank (Prev)": 30, "Code": "NoCode 21", "Name": "LO YUN-CHENG", "Birth Year": 2554, "Team": "มหาวิทยาลัยธนบุรี", "Age": 15, "NEW POINT JAN 26": 214.0, "Chonburi PAO 2026": 0.0, "Yasothon Open 2026": 0.0, "Total Point": 214.0}, {"Rank": 36, "Rank (Prev)": 39, "Code": "TH18646", "Name": "นโม สมานวงษ์", "Birth Year": 2552, "Team": "สโมสรเทเบิลเทนนิสตำรวจ", "Age": 17, "NEW POINT JAN 26": 143.78, "Chonburi PAO 2026": 63.2, "Yasothon Open 2026": 0.0, "Total Point": 206.98}, {"Rank": 37, "Rank (Prev)": 33, "Code": "NoCode 32", "Name": "CHANG SHENG-YUEH", "Birth Year": 2553, "Team": "มหาวิทยาลัยธนบุรี", "Age": 16, "NEW POINT JAN 26": 187.6, "Chonburi PAO 2026": 0.0, "Yasothon Open 2026": 0.0, "Total Point": 187.6}, {"Rank": 38, "Rank (Prev)": 51, "Code": "TH20392", "Name": "ณัฐภัทร สุขแพทย์", "Birth Year": 2554, "Team": "Pin Academy", "Age": 15, "NEW POINT JAN 26": 88.4, "Chonburi PAO 2026": 92.0, "Yasothon Open 2026": 0.0, "Total Point": 180.4}, {"Rank": 39, "Rank (Prev)": 36, "Code": "TH20280", "Name": "กิตติ์ธเนศ ลิ้มประเสริฐ", "Birth Year": 2552, "Team": "สโมสรกีฬาเซ็นทรัล", "Age": 17, "NEW POINT JAN 26": 154.99, "Chonburi PAO 2026": 20.0, "Yasothon Open 2026": 0.0, "Total Point": 174.99}, {"Rank": 40, "Rank (Prev)": 38, "Code": "TH20378", "Name": "ณัฏฐวัฒน์ หอวรรณภากรณ์", "Birth Year": 2552, "Team": "สโมสรเทเบิลเทนนิสพิษณุโลก", "Age": 17, "NEW POINT JAN 26": 144.1, "Chonburi PAO 2026": 20.0, "Yasothon Open 2026": 0.0, "Total Point": 164.1}, {"Rank": 41, "Rank (Prev)": 35, "Code": "NoCode 52", "Name": "ณัฎฐากร ชาวดร", "Birth Year": 2553, "Team": "pingpong K-O tech", "Age": 16, "NEW POINT JAN 26": 155.0, "Chonburi PAO 2026": 0.0, "Yasothon Open 2026": 0.0, "Total Point": 155.0}, {"Rank": 42, "Rank (Prev)": 37, "Code": "NoCode 58", "Name": "วีรภัทร์ อุปเสน", "Birth Year": 2552, "Team": "ยิมสามบาท เชียงใหม่", "Age": 17, "NEW POINT JAN 26": 148.9, "Chonburi PAO 2026": 0.0, "Yasothon Open 2026": 0.0, "Total Point": 148.9}, {"Rank": 43, "Rank (Prev)": 118, "Code": "LA20225", "Name": "XAYSANA XAYSAVATH", "Birth Year": 2555, "Team": "SV", "Age": 14, "NEW POINT JAN 26": 10.0, "Chonburi PAO 2026": 135.2, "Yasothon Open 2026": 0.0, "Total Point": 145.2}, {"Rank": 44, "Rank (Prev)": 41, "Code": "NoCode 61", "Name": "รวิภาส เจียมใจ", "Birth Year": 2553, "Team": "ALBATROS", "Age": 16, "NEW POINT JAN 26": 142.55, "Chonburi PAO 2026": 0.0, "Yasothon Open 2026": 0.0, "Total Point": 142.55}, {"Rank": 45, "Rank (Prev)": 42, "Code": "NoCode 62", "Name": "LU SHIH-YUAN", "Birth Year": 2554, "Team": "มหาวิทยาลัยธนบุรี", "Age": 15, "NEW POINT JAN 26": 139.6, "Chonburi PAO 2026": 0.0, "Yasothon Open 2026": 0.0, "Total Point": 139.6}, {"Rank": 46, "Rank (Prev)": 43, "Code": "NoCode 63", "Name": "จิตติพัฒน์ มะโนชัย", "Birth Year": 2553, "Team": "ไทยรุ่ง", "Age": 16, "NEW POINT JAN 26": 130.6, "Chonburi PAO 2026": 0.0, "Yasothon Open 2026": 0.0, "Total Point": 130.6}, {"Rank": 46, "Rank (Prev)": 43, "Code": "TH18895", "Name": "เมธาวิชย์ แสนสิทธิ์", "Birth Year": 2554, "Team": "สโมสรกีฬาเซ็นทรัล", "Age": 15, "NEW POINT JAN 26": 130.6, "Chonburi PAO 2026": 0.0, "Yasothon Open 2026": 0.0, "Total Point": 130.6}, {"Rank": 47, "Rank (Prev)": 45, "Code": "TH20295", "Name": "ภาคีย์นันท์ แก้วอุ่นเรือน", "Birth Year": 2554, "Team": "ไทยรุ่ง", "Age": 15, "NEW POINT JAN 26": 110.2, "Chonburi PAO 2026": 20.0, "Yasothon Open 2026": 0.0, "Total Point": 130.2}, {"Rank": 48, "Rank (Prev)": 46, "Code": "TH19326", "Name": "ชวัลวิทย์ ฉิมเจริญ", "Birth Year": 2552, "Team": "สาธิตประสานมิตร", "Age": 17, "NEW POINT JAN 26": 109.38, "Chonburi PAO 2026": 20.0, "Yasothon Open 2026": 0.0, "Total Point": 129.38}, {"Rank": 49, "Rank (Prev)": 48, "Code": "TH19329", "Name": "บรรณวัฒน์ ญาณสิทธิวิวัฒน์", "Birth Year": 2552, "Team": "สาธิตประสานมิตร", "Age": 17, "NEW POINT JAN 26": 100.0, "Chonburi PAO 2026": 20.0, "Yasothon Open 2026": 0.0, "Total Point": 120.0}, {"Rank": 50, "Rank (Prev)": 49, "Code": "TH19226", "Name": "จักรพงศ์ บุญประคอง", "Birth Year": 2554, "Team": "มหาวิทยาลัยธนบุรี", "Age": 15, "NEW POINT JAN 26": 95.8, "Chonburi PAO 2026": 20.0, "Yasothon Open 2026": 0.0, "Total Point": 115.8}, {"Rank": 51, "Rank (Prev)": 44, "Code": "NoCode 64", "Name": "WANG WEI-HSIANG", "Birth Year": 2552, "Team": "มหาวิทยาลัยธนบุรี", "Age": 17, "NEW POINT JAN 26": 115.6, "Chonburi PAO 2026": 0.0, "Yasothon Open 2026": 0.0, "Total Point": 115.6}, {"Rank": 52, "Rank (Prev)": 50, "Code": "TH10003", "Name": "ธีระ มัชชะ", "Birth Year": 2552, "Team": "โรงเรียนกีฬากรุงเทพ", "Age": 17, "NEW POINT JAN 26": 95.35, "Chonburi PAO 2026": 20.0, "Yasothon Open 2026": 0.0, "Total Point": 115.35}, {"Rank": 53, "Rank (Prev)": 47, "Code": "NoCode 66", "Name": "มรุพงศ์ กันธะรส", "Birth Year": 2553, "Team": "pingpong K-O tech", "Age": 16, "NEW POINT JAN 26": 107.45, "Chonburi PAO 2026": 0.0, "Yasothon Open 2026": 0.0, "Total Point": 107.45}, {"Rank": 54, "Rank (Prev)": "-", "Code": "TH19871", "Name": "ระพีพัฒน์ ทรัพย์สิน", "Birth Year": 2555, "Team": "สโมสรกีฬาเซ็นทรัล", "Age": 14, "NEW POINT JAN 26": 0.0, "Chonburi PAO 2026": 63.2, "Yasothon Open 2026": 44.0, "Total Point": 107.2}, {"Rank": 55, "Rank (Prev)": 52, "Code": "TH20211", "Name": "วัชรพงษ์ คำเขียน", "Birth Year": 2552, "Team": "โรงเรียนเทศบาลท่าโขลง 1", "Age": 17, "NEW POINT JAN 26": 85.5, "Chonburi PAO 2026": 20.0, "Yasothon Open 2026": 0.0, "Total Point": 105.5}, {"Rank": 56, "Rank (Prev)": 53, "Code": "TH19390", "Name": "ภูมิพัฒน์ วงษ์ทศรัตน์", "Birth Year": 2552, "Team": "เมืองทอง", "Age": 17, "NEW POINT JAN 26": 84.83, "Chonburi PAO 2026": 20.0, "Yasothon Open 2026": 0.0, "Total Point": 104.83}, {"Rank": 57, "Rank (Prev)": 54, "Code": "TH20391", "Name": "นนทิวรรธน์ ธารสิริสกุล", "Birth Year": 2553, "Team": "สาธิตประสานมิตร", "Age": 16, "NEW POINT JAN 26": 79.4, "Chonburi PAO 2026": 20.0, "Yasothon Open 2026": 0.0, "Total Point": 99.4}, {"Rank": 58, "Rank (Prev)": 57, "Code": "TH20186", "Name": "ชินดนัย จิราพงษ์", "Birth Year": 2552, "Team": "ไทยรุ่ง", "Age": 17, "NEW POINT JAN 26": 72.44, "Chonburi PAO 2026": 20.0, "Yasothon Open 2026": 0.0, "Total Point": 92.44}, {"Rank": 59, "Rank (Prev)": 58, "Code": "TH19412", "Name": "สิทธิไพศาล พาณิชย์พิศาล", "Birth Year": 2553, "Team": "H.P.P. Gym Samutsakhon", "Age": 16, "NEW POINT JAN 26": 72.25, "Chonburi PAO 2026": 20.0, "Yasothon Open 2026": 0.0, "Total Point": 92.25}, {"Rank": 60, "Rank (Prev)": 77, "Code": "TH18798", "Name": "ปรัชญา มาฆะวงศ์", "Birth Year": 2554, "Team": "สโมสรเทเบิลเทนนิสอิมพีเรียลสำโรง", "Age": 15, "NEW POINT JAN 26": 40.0, "Chonburi PAO 2026": 20.0, "Yasothon Open 2026": 32.0, "Total Point": 92.0}, {"Rank": 60, "Rank (Prev)": "-", "Code": "TH09981", "Name": "อทิตธรณ์ ธีรกิดากร", "Birth Year": 2555, "Team": "NEWWAY", "Age": 14, "NEW POINT JAN 26": 0.0, "Chonburi PAO 2026": 92.0, "Yasothon Open 2026": 0.0, "Total Point": 92.0}, {"Rank": 61, "Rank (Prev)": 60, "Code": "TH19178", "Name": "กมลวิชญ์ เหลืองสะอาด", "Birth Year": 2554, "Team": "เมืองทอง", "Age": 15, "NEW POINT JAN 26": 66.8, "Chonburi PAO 2026": 20.0, "Yasothon Open 2026": 0.0, "Total Point": 86.8}, {"Rank": 62, "Rank (Prev)": 63, "Code": "TH20066", "Name": "สุวิชัย ปิ่นแก้ว", "Birth Year": 2552, "Team": "H.P.P. Gym Samutsakhon", "Age": 17, "NEW POINT JAN 26": 64.06, "Chonburi PAO 2026": 20.0, "Yasothon Open 2026": 0.0, "Total Point": 84.06}, {"Rank": 63, "Rank (Prev)": "-", "Code": "TH19928", "Name": "ฐพชรกร อาญาเมือง", "Birth Year": 2555, "Team": "สโมสรเทเบิลเทนนิสบ้านปู", "Age": 14, "NEW POINT JAN 26": 0.0, "Chonburi PAO 2026": 20.0, "Yasothon Open 2026": 64.0, "Total Point": 84.0}, {"Rank": 64, "Rank (Prev)": 87, "Code": "TH18799", "Name": "ทีฆทัศน์ ตันตรงภักดิ์", "Birth Year": 2554, "Team": "สโมสรเทเบิลเทนนิสอิมพีเรียลสำโรง", "Age": 15, "NEW POINT JAN 26": 30.0, "Chonburi PAO 2026": 20.0, "Yasothon Open 2026": 32.0, "Total Point": 82.0}, {"Rank": 65, "Rank (Prev)": 65, "Code": "TH20350", "Name": "ยศพัทธ์ พิมสาร", "Birth Year": 2552, "Team": "สาธิตประสานมิตร", "Age": 17, "NEW POINT JAN 26": 60.0, "Chonburi PAO 2026": 20.0, "Yasothon Open 2026": 0.0, "Total Point": 80.0}, {"Rank": 66, "Rank (Prev)": 67, "Code": "TH19708", "Name": "วรภพ เชื้ออินทร์", "Birth Year": 2552, "Team": "ชมรมเทเบิลเทนนิสโรงเรียนนาหลวง", "Age": 17, "NEW POINT JAN 26": 59.92, "Chonburi PAO 2026": 20.0, "Yasothon Open 2026": 0.0, "Total Point": 79.92}, {"Rank": 67, "Rank (Prev)": 68, "Code": "TH19574", "Name": "ณัทกวี อ่อนท้วม", "Birth Year": 2554, "Team": "สาธิตประสานมิตร", "Age": 15, "NEW POINT JAN 26": 57.8, "Chonburi PAO 2026": 20.0, "Yasothon Open 2026": 0.0, "Total Point": 77.8}, {"Rank": 68, "Rank (Prev)": 70, "Code": "TH19702", "Name": "คณินพ์วรรศ สมบูรณ์", "Birth Year": 2553, "Team": "ชมรมเทเบิลเทนนิสโรงเรียนนาหลวง", "Age": 16, "NEW POINT JAN 26": 54.9, "Chonburi PAO 2026": 20.0, "Yasothon Open 2026": 0.0, "Total Point": 74.9}, {"Rank": 69, "Rank (Prev)": 56, "Code": "TH20080", "Name": "ภัทร ภัทรหิรัญ", "Birth Year": 2554, "Team": "Pipeline Bundle Service", "Age": 15, "NEW POINT JAN 26": 74.4, "Chonburi PAO 2026": 0.0, "Yasothon Open 2026": 0.0, "Total Point": 74.4}, {"Rank": 70, "Rank (Prev)": 58, "Code": "NoCode 67", "Name": "ฐนันพงศ์ เนยสูงเนิน", "Birth Year": 2552, "Team": "สโมสรเทเบิลเทนนิสตำรวจ", "Age": 17, "NEW POINT JAN 26": 72.25, "Chonburi PAO 2026": 0.0, "Yasothon Open 2026": 0.0, "Total Point": 72.25}, {"Rank": 71, "Rank (Prev)": 59, "Code": "NoCode 68", "Name": "Khenan Egli", "Birth Year": 2552, "Team": "ยิมสามบาท เชียงใหม่", "Age": 17, "NEW POINT JAN 26": 70.5, "Chonburi PAO 2026": 0.0, "Yasothon Open 2026": 0.0, "Total Point": 70.5}, {"Rank": 71, "Rank (Prev)": 72, "Code": "TH10002", "Name": "ฑีฆายุ ท่าวิลัย", "Birth Year": 2552, "Team": "โรงเรียนกีฬากรุงเทพ", "Age": 17, "NEW POINT JAN 26": 50.5, "Chonburi PAO 2026": 20.0, "Yasothon Open 2026": 0.0, "Total Point": 70.5}, {"Rank": 72, "Rank (Prev)": 73, "Code": "TH20110", "Name": "พัชรวัฒน์ หยั่งถึงนพชัย", "Birth Year": 2554, "Team": "มหาวิทยาลัยธนบุรี", "Age": 15, "NEW POINT JAN 26": 50.0, "Chonburi PAO 2026": 20.0, "Yasothon Open 2026": 0.0, "Total Point": 70.0}, {"Rank": 72, "Rank (Prev)": 73, "Code": "TH19352", "Name": "อิศราภาคย์ ทักษนนท์", "Birth Year": 2554, "Team": "สาธิตประสานมิตร", "Age": 15, "NEW POINT JAN 26": 50.0, "Chonburi PAO 2026": 20.0, "Yasothon Open 2026": 0.0, "Total Point": 70.0}, {"Rank": 73, "Rank (Prev)": 61, "Code": "TH19335", "Name": "ประภวิษณุ์ ทองสว่าง", "Birth Year": 2553, "Team": "เมืองทอง", "Age": 16, "NEW POINT JAN 26": 65.0, "Chonburi PAO 2026": 0.0, "Yasothon Open 2026": 0.0, "Total Point": 65.0}, {"Rank": 73, "Rank (Prev)": 61, "Code": "TH19911", "Name": "ชายศิริณ บุญสิริวัชรกุล", "Birth Year": 2552, "Team": "สโมสรเทเบิลเทนนิสบ้านปู", "Age": 17, "NEW POINT JAN 26": 65.0, "Chonburi PAO 2026": 0.0, "Yasothon Open 2026": 0.0, "Total Point": 65.0}, {"Rank": 74, "Rank (Prev)": 62, "Code": "TH09974", "Name": "จุตติธัมม์ โฆษิตากาศ", "Birth Year": 2553, "Team": "เมืองทอง", "Age": 16, "NEW POINT JAN 26": 64.5, "Chonburi PAO 2026": 0.0, "Yasothon Open 2026": 0.0, "Total Point": 64.5}, {"Rank": 75, "Rank (Prev)": 64, "Code": "TH18253", "Name": "ศุภกร กาศักดิ์", "Birth Year": 2552, "Team": "ปิงปองบุรีรมย์", "Age": 17, "NEW POINT JAN 26": 64.0, "Chonburi PAO 2026": 0.0, "Yasothon Open 2026": 0.0, "Total Point": 64.0}, {"Rank": 76, "Rank (Prev)": "-", "Code": "TH18134", "Name": "ติณห์ พิทักษานุรัตน์", "Birth Year": 2555, "Team": "สโมสรกีฬาเซ็นทรัล", "Age": 14, "NEW POINT JAN 26": 0.0, "Chonburi PAO 2026": 63.2, "Yasothon Open 2026": 0.0, "Total Point": 63.2}, {"Rank": 76, "Rank (Prev)": "-", "Code": "TH19866", "Name": "ปีส์มังกร หิรัญญสมบัติ", "Birth Year": 2555, "Team": "สโมสรเทเบิลเทนนิสบ้านปู", "Age": 14, "NEW POINT JAN 26": 0.0, "Chonburi PAO 2026": 63.2, "Yasothon Open 2026": 0.0, "Total Point": 63.2}, {"Rank": 76, "Rank (Prev)": "-", "Code": "TH20351", "Name": "กิตติวรรธ จอมคีรี", "Birth Year": 2555, "Team": "Pattaya United ", "Age": 14, "NEW POINT JAN 26": 0.0, "Chonburi PAO 2026": 63.2, "Yasothon Open 2026": 0.0, "Total Point": 63.2}, {"Rank": 76, "Rank (Prev)": "-", "Code": "ID20224", "Name": "Julius Wong", "Birth Year": 2552, "Team": "SISB", "Age": 17, "NEW POINT JAN 26": 0.0, "Chonburi PAO 2026": 63.2, "Yasothon Open 2026": 0.0, "Total Point": 63.2}, {"Rank": 77, "Rank (Prev)": 65, "Code": "TH19678", "Name": "รัชยุฒม์ กิตติจิรวงศ์", "Birth Year": 2553, "Team": "ไทยรุ่ง", "Age": 16, "NEW POINT JAN 26": 60.0, "Chonburi PAO 2026": 0.0, "Yasothon Open 2026": 0.0, "Total Point": 60.0}, {"Rank": 77, "Rank (Prev)": 77, "Code": "TH20296", "Name": "ภูมินันท์ แก้วอุ่นเรือน", "Birth Year": 2554, "Team": "ไทยรุ่ง", "Age": 15, "NEW POINT JAN 26": 40.0, "Chonburi PAO 2026": 20.0, "Yasothon Open 2026": 0.0, "Total Point": 60.0}, {"Rank": 77, "Rank (Prev)": 77, "Code": "TH09999", "Name": "ธนวัฒน์ สุริวงค์", "Birth Year": 2552, "Team": "โรงเรียนกีฬากรุงเทพ", "Age": 17, "NEW POINT JAN 26": 40.0, "Chonburi PAO 2026": 20.0, "Yasothon Open 2026": 0.0, "Total Point": 60.0}, {"Rank": 78, "Rank (Prev)": 66, "Code": "TH20294", "Name": "พีรพงศ์ อ่อนหวาน", "Birth Year": 2553, "Team": "สโมสรกีฬาเซ็นทรัล", "Age": 16, "NEW POINT JAN 26": 59.93, "Chonburi PAO 2026": 0.0, "Yasothon Open 2026": 0.0, "Total Point": 59.93}, {"Rank": 79, "Rank (Prev)": 79, "Code": "TH20207", "Name": "ทวีชัย ทะวิลา", "Birth Year": 2553, "Team": "โรงเรียนเทศบาลท่าโขลง 1", "Age": 16, "NEW POINT JAN 26": 39.06, "Chonburi PAO 2026": 20.0, "Yasothon Open 2026": 0.0, "Total Point": 59.06}, {"Rank": 80, "Rank (Prev)": 80, "Code": "TH20323", "Name": "ฐปนรรฆ์ สงโสม", "Birth Year": 2553, "Team": "สโมสรกีฬาเซ็นทรัล", "Age": 16, "NEW POINT JAN 26": 38.59, "Chonburi PAO 2026": 20.0, "Yasothon Open 2026": 0.0, "Total Point": 58.59}, {"Rank": 81, "Rank (Prev)": 55, "Code": "TH20160", "Name": "ธนกฤต ลิขิตหัตถศิลป", "Birth Year": 2552, "Team": "ปิงปองระยองคลับ", "Age": 17, "NEW POINT JAN 26": 75.5, "Chonburi PAO 2026": -20.0, "Yasothon Open 2026": 0.0, "Total Point": 55.5}, {"Rank": 81, "Rank (Prev)": 82, "Code": "TH20435", "Name": "ขจรพล เขตกุล", "Birth Year": 2552, "Team": "RIDER CHONBURI", "Age": 17, "NEW POINT JAN 26": 35.5, "Chonburi PAO 2026": 20.0, "Yasothon Open 2026": 0.0, "Total Point": 55.5}, {"Rank": 82, "Rank (Prev)": 69, "Code": "NoCode 69", "Name": "BHONE WAI YAN MYOE", "Birth Year": 2554, "Team": "Pin Academy", "Age": 15, "NEW POINT JAN 26": 55.0, "Chonburi PAO 2026": 0.0, "Yasothon Open 2026": 0.0, "Total Point": 55.0}, {"Rank": 83, "Rank (Prev)": 70, "Code": "NoCode 70", "Name": "เดวิด มะโลน", "Birth Year": 2552, "Team": "สโมสรกีฬาบีบีจี", "Age": 17, "NEW POINT JAN 26": 54.9, "Chonburi PAO 2026": 0.0, "Yasothon Open 2026": 0.0, "Total Point": 54.9}, {"Rank": 84, "Rank (Prev)": 71, "Code": "NoCode 71", "Name": "กฤษณ์พีรัช รพีวิมลศุภกร", "Birth Year": 2552, "Team": "ชมรมเทเบิลเทนนิสช่องฟ้าซินเซิงวาณิชบำรุง", "Age": 17, "NEW POINT JAN 26": 52.66, "Chonburi PAO 2026": 0.0, "Yasothon Open 2026": 0.0, "Total Point": 52.66}, {"Rank": 85, "Rank (Prev)": 87, "Code": "TH20325", "Name": "พีรพรรดิ์ รุ่งคล้าย", "Birth Year": 2554, "Team": "มหาวิทยาลัยธนบุรี", "Age": 15, "NEW POINT JAN 26": 30.0, "Chonburi PAO 2026": 20.0, "Yasothon Open 2026": 0.0, "Total Point": 50.0}, {"Rank": 86, "Rank (Prev)": 74, "Code": "NoCode 73", "Name": "พชรกฤษฎิ์ พร้อมจักรสิงห์", "Birth Year": 2553, "Team": "ชมรมเทเบิลเทนนิสโรงเรียนนาหลวง", "Age": 16, "NEW POINT JAN 26": 49.97, "Chonburi PAO 2026": 0.0, "Yasothon Open 2026": 0.0, "Total Point": 49.97}, {"Rank": 87, "Rank (Prev)": 75, "Code": "NoCode 75", "Name": "เอกอาทิตย์ หงษ์นวล", "Birth Year": 2552, "Team": "ชมรมเทเบิลเทนนิสช่องฟ้าซินเซิงวาณิชบำรุง", "Age": 17, "NEW POINT JAN 26": 49.91, "Chonburi PAO 2026": 0.0, "Yasothon Open 2026": 0.0, "Total Point": 49.91}, {"Rank": 88, "Rank (Prev)": 76, "Code": "NoCode 76", "Name": "ภาคภูมิ ทองกำไร", "Birth Year": 2552, "Team": "สโมสรเทเบิลเทนนิสตำรวจ", "Age": 17, "NEW POINT JAN 26": 44.85, "Chonburi PAO 2026": 0.0, "Yasothon Open 2026": 0.0, "Total Point": 44.85}, {"Rank": 88, "Rank (Prev)": 76, "Code": "TH20156", "Name": "ภูผา คุณจันทรโชติ", "Birth Year": 2553, "Team": "Magic Pingpong", "Age": 16, "NEW POINT JAN 26": 44.85, "Chonburi PAO 2026": 0.0, "Yasothon Open 2026": 0.0, "Total Point": 44.85}, {"Rank": 89, "Rank (Prev)": 96, "Code": "TH19365", "Name": "ตรัยภูมิ ติณณจิรางกูร", "Birth Year": 2553, "Team": "สาธิตประสานมิตร", "Age": 16, "NEW POINT JAN 26": 24.53, "Chonburi PAO 2026": 20.0, "Yasothon Open 2026": 0.0, "Total Point": 44.53}, {"Rank": 90, "Rank (Prev)": "-", "Code": "TH20649", "Name": "พรหมพิริยะ สารีรัตน์", "Birth Year": 2555, "Team": "สโมสรเทเบิลเทนนิสบ้านปู", "Age": 14, "NEW POINT JAN 26": 0.0, "Chonburi PAO 2026": 0.0, "Yasothon Open 2026": 44.0, "Total Point": 44.0}, {"Rank": 91, "Rank (Prev)": 77, "Code": "TH18473", "Name": "ธนกฤต วงศ์จันทร์", "Birth Year": 2553, "Team": "ยิมสามบาท เชียงใหม่", "Age": 16, "NEW POINT JAN 26": 40.0, "Chonburi PAO 2026": 0.0, "Yasothon Open 2026": 0.0, "Total Point": 40.0}, {"Rank": 91, "Rank (Prev)": 77, "Code": "TH18539", "Name": "ภาณฤทธา บ่อคำ", "Birth Year": 2554, "Team": "มหาวิทยาลัยธนบุรี", "Age": 15, "NEW POINT JAN 26": 40.0, "Chonburi PAO 2026": 0.0, "Yasothon Open 2026": 0.0, "Total Point": 40.0}, {"Rank": 91, "Rank (Prev)": 102, "Code": "TH19134", "Name": "ภณสิริ ลืนคำ", "Birth Year": 2554, "Team": "ชมรมเทเบิลเทนนิสช่องฟ้าซินเซิงวาณิชบำรุง", "Age": 15, "NEW POINT JAN 26": 20.0, "Chonburi PAO 2026": 20.0, "Yasothon Open 2026": 0.0, "Total Point": 40.0}, {"Rank": 91, "Rank (Prev)": 102, "Code": "TH19268", "Name": "พิตตินันท์ ภธากุล", "Birth Year": 2552, "Team": "DUK. Ubon", "Age": 17, "NEW POINT JAN 26": 20.0, "Chonburi PAO 2026": 20.0, "Yasothon Open 2026": 0.0, "Total Point": 40.0}, {"Rank": 91, "Rank (Prev)": 102, "Code": "TH19471", "Name": "ปองคุณ จินามอย", "Birth Year": 2554, "Team": "NEWWAY", "Age": 15, "NEW POINT JAN 26": 20.0, "Chonburi PAO 2026": 20.0, "Yasothon Open 2026": 0.0, "Total Point": 40.0}, {"Rank": 91, "Rank (Prev)": 102, "Code": "TH20226", "Name": "นิติธร พฤกษโสภี", "Birth Year": 2554, "Team": "โรงเรียนเทศบาลท่าโขลง 1", "Age": 15, "NEW POINT JAN 26": 20.0, "Chonburi PAO 2026": 20.0, "Yasothon Open 2026": 0.0, "Total Point": 40.0}, {"Rank": 92, "Rank (Prev)": 103, "Code": "TH20166", "Name": "พงศวรรธก์ แจ้งชัด", "Birth Year": 2553, "Team": "ปิงปองระยองคลับ", "Age": 16, "NEW POINT JAN 26": 19.98, "Chonburi PAO 2026": 20.0, "Yasothon Open 2026": 0.0, "Total Point": 39.98}, {"Rank": 93, "Rank (Prev)": 78, "Code": "TH20229", "Name": "ชุณห์พิพัฒน์ ชัยวรศิลป์", "Birth Year": 2553, "Team": "โรงเรียนเทศบาลท่าโขลง 1", "Age": 16, "NEW POINT JAN 26": 39.06, "Chonburi PAO 2026": 0.0, "Yasothon Open 2026": 0.0, "Total Point": 39.06}, {"Rank": 94, "Rank (Prev)": 82, "Code": "NoCode 80", "Name": "ภาณุพงศ์ เบิกขุนทด", "Birth Year": 2553, "Team": "NCN TABEL TENNIS TEAM", "Age": 16, "NEW POINT JAN 26": 35.5, "Chonburi PAO 2026": 0.0, "Yasothon Open 2026": 0.0, "Total Point": 35.5}, {"Rank": 95, "Rank (Prev)": 83, "Code": "NoCode 81", "Name": "ธนกฤต รุ้งกระดี่", "Birth Year": 2552, "Team": "สโมสรเทเบิลเทนนิสตำรวจ", "Age": 17, "NEW POINT JAN 26": 35.0, "Chonburi PAO 2026": 0.0, "Yasothon Open 2026": 0.0, "Total Point": 35.0}, {"Rank": 95, "Rank (Prev)": 83, "Code": "NoCode 82", "Name": "อิทธิพล ภาคพฤกษ์", "Birth Year": 2552, "Team": "สโมสรกีฬาบีบีจี", "Age": 17, "NEW POINT JAN 26": 35.0, "Chonburi PAO 2026": 0.0, "Yasothon Open 2026": 0.0, "Total Point": 35.0}, {"Rank": 96, "Rank (Prev)": 84, "Code": "NoCode 83", "Name": "Senglatsamee Keohuengsuk", "Birth Year": 2553, "Team": "สโมสรกีฬาเซ็นทรัล", "Age": 16, "NEW POINT JAN 26": 33.35, "Chonburi PAO 2026": 0.0, "Yasothon Open 2026": 0.0, "Total Point": 33.35}, {"Rank": 97, "Rank (Prev)": 85, "Code": "NoCode 84", "Name": "อิทธิกร อับดุลย์", "Birth Year": 2553, "Team": "มหาวิทยาลัยธนบุรี", "Age": 16, "NEW POINT JAN 26": 32.52, "Chonburi PAO 2026": 0.0, "Yasothon Open 2026": 0.0, "Total Point": 32.52}, {"Rank": 98, "Rank (Prev)": "-", "Code": "TH20958", "Name": "ธนกฤต ชมภูวิเศษ", "Birth Year": 2555, "Team": "เมืองทอง", "Age": 14, "NEW POINT JAN 26": 0.0, "Chonburi PAO 2026": 0.0, "Yasothon Open 2026": 32.0, "Total Point": 32.0}, {"Rank": 99, "Rank (Prev)": 86, "Code": "NoCode 85", "Name": "พิมไท พิมลา", "Birth Year": 2552, "Team": "สโมสรกีฬาเซ็นทรัล", "Age": 17, "NEW POINT JAN 26": 31.7, "Chonburi PAO 2026": 0.0, "Yasothon Open 2026": 0.0, "Total Point": 31.7}, {"Rank": 100, "Rank (Prev)": 87, "Code": "NoCode 86", "Name": "ชูวงค์ เกาะแก้ว", "Birth Year": 2554, "Team": "มหาวิทยาลัยธนบุรี", "Age": 15, "NEW POINT JAN 26": 30.0, "Chonburi PAO 2026": 0.0, "Yasothon Open 2026": 0.0, "Total Point": 30.0}, {"Rank": 100, "Rank (Prev)": 87, "Code": "NoCode 87", "Name": "ฐาปกรณ์ อารีพันธ์", "Birth Year": 2554, "Team": "สโมสรเทเบิลเทนนิสอิมพีเรียลสำโรง", "Age": 15, "NEW POINT JAN 26": 30.0, "Chonburi PAO 2026": 0.0, "Yasothon Open 2026": 0.0, "Total Point": 30.0}, {"Rank": 100, "Rank (Prev)": 87, "Code": "NoCode 88", "Name": "นาราภัทร เถื่อนศรี", "Birth Year": 2554, "Team": "Magic Pingpong", "Age": 15, "NEW POINT JAN 26": 30.0, "Chonburi PAO 2026": 0.0, "Yasothon Open 2026": 0.0, "Total Point": 30.0}, {"Rank": 100, "Rank (Prev)": 87, "Code": "TH18409", "Name": "ธณกฤต ลีลาสถาพร", "Birth Year": 2554, "Team": "NEWWAY", "Age": 15, "NEW POINT JAN 26": 30.0, "Chonburi PAO 2026": 0.0, "Yasothon Open 2026": 0.0, "Total Point": 30.0}, {"Rank": 100, "Rank (Prev)": 118, "Code": "NoCode 36", "Name": "ศุภกร สิมมา", "Birth Year": 2553, "Team": "องค์การบริหารส่วนจังหวัดชลบุรี", "Age": 16, "NEW POINT JAN 26": 10.0, "Chonburi PAO 2026": 20.0, "Yasothon Open 2026": 0.0, "Total Point": 30.0}, {"Rank": 100, "Rank (Prev)": 118, "Code": "TH19396", "Name": "ธนภัทร สุขประเสริฐ", "Birth Year": 2554, "Team": "เทเบิลเทนนิสจังหวัดชลบุรี", "Age": 15, "NEW POINT JAN 26": 10.0, "Chonburi PAO 2026": 20.0, "Yasothon Open 2026": 0.0, "Total Point": 30.0}, {"Rank": 100, "Rank (Prev)": 118, "Code": "TH19711", "Name": "คณิศร ศรีขำ", "Birth Year": 2554, "Team": "ชมรมเทเบิลเทนนิสโรงเรียนนาหลวง", "Age": 15, "NEW POINT JAN 26": 10.0, "Chonburi PAO 2026": 20.0, "Yasothon Open 2026": 0.0, "Total Point": 30.0}, {"Rank": 100, "Rank (Prev)": 118, "Code": "TH19700", "Name": "มนัญชัย โตถาวร", "Birth Year": 2554, "Team": "ชมรมเทเบิลเทนนิสโรงเรียนนาหลวง", "Age": 15, "NEW POINT JAN 26": 10.0, "Chonburi PAO 2026": 20.0, "Yasothon Open 2026": 0.0, "Total Point": 30.0}, {"Rank": 100, "Rank (Prev)": 118, "Code": "TH20092", "Name": "ณัฐชนน นิ่มพินิจ", "Birth Year": 2554, "Team": "H.P.P. Gym Samutsakhon", "Age": 15, "NEW POINT JAN 26": 10.0, "Chonburi PAO 2026": 20.0, "Yasothon Open 2026": 0.0, "Total Point": 30.0}, {"Rank": 100, "Rank (Prev)": 118, "Code": "TH20097", "Name": "สรวิศ นุ่มสุข", "Birth Year": 2554, "Team": "H.P.P. Gym Samutsakhon", "Age": 15, "NEW POINT JAN 26": 10.0, "Chonburi PAO 2026": 20.0, "Yasothon Open 2026": 0.0, "Total Point": 30.0}, {"Rank": 100, "Rank (Prev)": 118, "Code": "TH20104", "Name": "สมิทธิ์ เดชวิไลศรี", "Birth Year": 2554, "Team": "ปิงปองระยองคลับ", "Age": 15, "NEW POINT JAN 26": 10.0, "Chonburi PAO 2026": 20.0, "Yasothon Open 2026": 0.0, "Total Point": 30.0}, {"Rank": 100, "Rank (Prev)": 118, "Code": "TH20419", "Name": "ศุภกร สิมมา", "Birth Year": 2553, "Team": "องค์การบริหารส่วนจังหวัดชลบุรี", "Age": 16, "NEW POINT JAN 26": 10.0, "Chonburi PAO 2026": 20.0, "Yasothon Open 2026": 0.0, "Total Point": 30.0}, {"Rank": 101, "Rank (Prev)": 88, "Code": "NoCode 90", "Name": "ธีรภัทร หนูรักษ์", "Birth Year": 2553, "Team": "มหาวิทยาลัยธนบุรี", "Age": 16, "NEW POINT JAN 26": 28.3, "Chonburi PAO 2026": 0.0, "Yasothon Open 2026": 0.0, "Total Point": 28.3}, {"Rank": 102, "Rank (Prev)": 89, "Code": "NoCode 91", "Name": "ธิติ รวมพล", "Birth Year": 2553, "Team": "PPG 101", "Age": 16, "NEW POINT JAN 26": 27.45, "Chonburi PAO 2026": 0.0, "Yasothon Open 2026": 0.0, "Total Point": 27.45}, {"Rank": 103, "Rank (Prev)": 90, "Code": "NoCode 92", "Name": "สมพร กำลังพร", "Birth Year": 2554, "Team": "สโมสรกีฬาบีบีจี", "Age": 15, "NEW POINT JAN 26": 26.6, "Chonburi PAO 2026": 0.0, "Yasothon Open 2026": 0.0, "Total Point": 26.6}, {"Rank": 104, "Rank (Prev)": 91, "Code": "NoCode 93", "Name": "รพีภัทร ปาลวงษ์", "Birth Year": 2552, "Team": "ชมรมเทเบิลเทนนิสจังหวัดตรัง", "Age": 17, "NEW POINT JAN 26": 26.0, "Chonburi PAO 2026": 0.0, "Yasothon Open 2026": 0.0, "Total Point": 26.0}, {"Rank": 105, "Rank (Prev)": 92, "Code": "NoCode 94", "Name": "ชยพล นาสี", "Birth Year": 2552, "Team": "Prospin Club", "Age": 17, "NEW POINT JAN 26": 25.0, "Chonburi PAO 2026": 0.0, "Yasothon Open 2026": 0.0, "Total Point": 25.0}, {"Rank": 105, "Rank (Prev)": 92, "Code": "NoCode 95", "Name": "ชิษณุพงศ์ ปั้นนาค", "Birth Year": 2553, "Team": "BPP Table Tennis House", "Age": 16, "NEW POINT JAN 26": 25.0, "Chonburi PAO 2026": 0.0, "Yasothon Open 2026": 0.0, "Total Point": 25.0}, {"Rank": 105, "Rank (Prev)": 92, "Code": "NoCode 96", "Name": "ณชพัฒน์ แก้วอ่อง", "Birth Year": 2552, "Team": "เทเบิลเทนนิสท.5หนองผักก้าม", "Age": 17, "NEW POINT JAN 26": 25.0, "Chonburi PAO 2026": 0.0, "Yasothon Open 2026": 0.0, "Total Point": 25.0}, {"Rank": 105, "Rank (Prev)": 92, "Code": "NoCode 97", "Name": "ณัฏฐกิตติ์ เงินจันทร์", "Birth Year": 2553, "Team": "สโมสรเทเบิลเทนนิสพิษณุโลก", "Age": 16, "NEW POINT JAN 26": 25.0, "Chonburi PAO 2026": 0.0, "Yasothon Open 2026": 0.0, "Total Point": 25.0}, {"Rank": 105, "Rank (Prev)": 92, "Code": "NoCode 98", "Name": "ธนากร ทาวงศ์ยศ", "Birth Year": 2552, "Team": "มหาวิทยาลัยการกีฬาแห่งชาติ วิทยาเขตลำปาง", "Age": 17, "NEW POINT JAN 26": 25.0, "Chonburi PAO 2026": 0.0, "Yasothon Open 2026": 0.0, "Total Point": 25.0}, {"Rank": 105, "Rank (Prev)": 92, "Code": "NoCode 99", "Name": "พงศ์พล เพียนอก", "Birth Year": 2553, "Team": "NCN TABEL TENNIS TEAM", "Age": 16, "NEW POINT JAN 26": 25.0, "Chonburi PAO 2026": 0.0, "Yasothon Open 2026": 0.0, "Total Point": 25.0}, {"Rank": 106, "Rank (Prev)": 93, "Code": "NoCode 100", "Name": "ณัฐพงษ์ ดูสันเทียะ", "Birth Year": 2553, "Team": "Chaiyaphum table tennis Team", "Age": 16, "NEW POINT JAN 26": 24.75, "Chonburi PAO 2026": 0.0, "Yasothon Open 2026": 0.0, "Total Point": 24.75}, {"Rank": 107, "Rank (Prev)": 94, "Code": "NoCode 102", "Name": "จิรภัทร ทองพลับ", "Birth Year": 2553, "Team": "สโมสรเทเบิลเทนนิสพิษณุโลก", "Age": 16, "NEW POINT JAN 26": 24.62, "Chonburi PAO 2026": 0.0, "Yasothon Open 2026": 0.0, "Total Point": 24.62}, {"Rank": 108, "Rank (Prev)": 95, "Code": "NoCode 103", "Name": "จุลวิทย์ เผือกทอง", "Birth Year": 2553, "Team": "ยิมสามบาท เชียงใหม่", "Age": 16, "NEW POINT JAN 26": 24.56, "Chonburi PAO 2026": 0.0, "Yasothon Open 2026": 0.0, "Total Point": 24.56}, {"Rank": 109, "Rank (Prev)": 97, "Code": "NoCode 104", "Name": "LOO ZHEN XIN", "Birth Year": 2552, "Team": "มหาวิทยาลัยธนบุรี", "Age": 17, "NEW POINT JAN 26": 24.5, "Chonburi PAO 2026": 0.0, "Yasothon Open 2026": 0.0, "Total Point": 24.5}, {"Rank": 110, "Rank (Prev)": 98, "Code": "NoCode 105", "Name": "TEY HONG​ YU", "Birth Year": 2552, "Team": "สโมสรกีฬาเซ็นทรัล", "Age": 17, "NEW POINT JAN 26": 22.65, "Chonburi PAO 2026": 0.0, "Yasothon Open 2026": 0.0, "Total Point": 22.65}, {"Rank": 111, "Rank (Prev)": 99, "Code": "TH20161", "Name": "นทีภัทร ขันปล้อง", "Birth Year": 2553, "Team": "Magic Pingpong", "Age": 16, "NEW POINT JAN 26": 22.57, "Chonburi PAO 2026": 0.0, "Yasothon Open 2026": 0.0, "Total Point": 22.57}, {"Rank": 112, "Rank (Prev)": 100, "Code": "TH19346", "Name": "คณพศ เตยะราชกุล", "Birth Year": 2552, "Team": "สาธิตมศว.ปทุมวัน", "Age": 17, "NEW POINT JAN 26": 22.5, "Chonburi PAO 2026": 0.0, "Yasothon Open 2026": 0.0, "Total Point": 22.5}, {"Rank": 113, "Rank (Prev)": 101, "Code": "NoCode 106", "Name": "พีรันธร สถาวร", "Birth Year": 2552, "Team": "-", "Age": 17, "NEW POINT JAN 26": 20.5, "Chonburi PAO 2026": 0.0, "Yasothon Open 2026": 0.0, "Total Point": 20.5}, {"Rank": 114, "Rank (Prev)": 102, "Code": "NoCode 107", "Name": "กิตติ​ศักดิ์​ วงศ์​แก้ว", "Birth Year": 2552, "Team": "ชมรมเทเบิลเทนนิสจังหวัดตราด", "Age": 17, "NEW POINT JAN 26": 20.0, "Chonburi PAO 2026": 0.0, "Yasothon Open 2026": 0.0, "Total Point": 20.0}, {"Rank": 114, "Rank (Prev)": 102, "Code": "NoCode 108", "Name": "ไกรวิชญ์ หลอ", "Birth Year": 2552, "Team": "-", "Age": 17, "NEW POINT JAN 26": 20.0, "Chonburi PAO 2026": 0.0, "Yasothon Open 2026": 0.0, "Total Point": 20.0}, {"Rank": 114, "Rank (Prev)": 102, "Code": "NoCode 109", "Name": "ณัฐดนัย รติรณกร", "Birth Year": 2552, "Team": "ห้างหุ้นส่วนจำกัด ซอฟต์แวร์ไทย", "Age": 17, "NEW POINT JAN 26": 20.0, "Chonburi PAO 2026": 0.0, "Yasothon Open 2026": 0.0, "Total Point": 20.0}, {"Rank": 114, "Rank (Prev)": 102, "Code": "NoCode 111", "Name": "ปรัตถ์สุทร ฉ่ำสดใส", "Birth Year": 2552, "Team": "โรงเรียนสาธิตมหาวิทยาลัยรามคำเเหง(ฝ่ายมัธยม)", "Age": 17, "NEW POINT JAN 26": 20.0, "Chonburi PAO 2026": 0.0, "Yasothon Open 2026": 0.0, "Total Point": 20.0}, {"Rank": 114, "Rank (Prev)": 102, "Code": "NoCode 112", "Name": "ปาณวัตร เวชศาสตร", "Birth Year": 2552, "Team": "ชมรมเทเบิลเทนนิสจังหวัดตราด", "Age": 17, "NEW POINT JAN 26": 20.0, "Chonburi PAO 2026": 0.0, "Yasothon Open 2026": 0.0, "Total Point": 20.0}, {"Rank": 114, "Rank (Prev)": 102, "Code": "NoCode 113", "Name": "พุทธิพงษ์ ธัมมศรัทธาวงศ์", "Birth Year": 2554, "Team": "KBTTC", "Age": 15, "NEW POINT JAN 26": 20.0, "Chonburi PAO 2026": 0.0, "Yasothon Open 2026": 0.0, "Total Point": 20.0}, {"Rank": 114, "Rank (Prev)": 102, "Code": "NoCode 114", "Name": "ภูริวัฒน์ พื้นบาท", "Birth Year": 2552, "Team": "-", "Age": 17, "NEW POINT JAN 26": 20.0, "Chonburi PAO 2026": 0.0, "Yasothon Open 2026": 0.0, "Total Point": 20.0}, {"Rank": 114, "Rank (Prev)": 102, "Code": "NoCode 115", "Name": "วิชญ์กรณ์ ลิ้มประเสริฐ", "Birth Year": 2554, "Team": "ปิงปองสมุทรสาคร", "Age": 15, "NEW POINT JAN 26": 20.0, "Chonburi PAO 2026": 0.0, "Yasothon Open 2026": 0.0, "Total Point": 20.0}, {"Rank": 114, "Rank (Prev)": 102, "Code": "NoCode 116", "Name": "ศุภณัฐ​ จันทร์​ละออ", "Birth Year": 2552, "Team": "ชมรมเทเบิลเทนนิสจังหวัดตราด", "Age": 17, "NEW POINT JAN 26": 20.0, "Chonburi PAO 2026": 0.0, "Yasothon Open 2026": 0.0, "Total Point": 20.0}, {"Rank": 114, "Rank (Prev)": 102, "Code": "NoCode 117", "Name": "อติเทพ ศรีทอง", "Birth Year": 2552, "Team": "ห้างหุ้นส่วนจำกัด ซอฟต์แวร์ไทย", "Age": 17, "NEW POINT JAN 26": 20.0, "Chonburi PAO 2026": 0.0, "Yasothon Open 2026": 0.0, "Total Point": 20.0}, {"Rank": 114, "Rank (Prev)": 102, "Code": "TH20162", "Name": "ณัฐวัฒน์ สายเปลี่ยน", "Birth Year": 2554, "Team": "Magic Pingpong", "Age": 15, "NEW POINT JAN 26": 20.0, "Chonburi PAO 2026": 0.0, "Yasothon Open 2026": 0.0, "Total Point": 20.0}, {"Rank": 114, "Rank (Prev)": "-", "Code": "TH20333", "Name": "ณธกร ข่วงอารินทร์", "Birth Year": 2554, "Team": "Pattaya United ", "Age": 15, "NEW POINT JAN 26": 0.0, "Chonburi PAO 2026": 20.0, "Yasothon Open 2026": 0.0, "Total Point": 20.0}, {"Rank": 114, "Rank (Prev)": "-", "Code": "TH20132", "Name": "เลิศพิสิทธิ์ พวงพันธ์", "Birth Year": 2554, "Team": "Spinning Star ", "Age": 15, "NEW POINT JAN 26": 0.0, "Chonburi PAO 2026": 20.0, "Yasothon Open 2026": 0.0, "Total Point": 20.0}, {"Rank": 114, "Rank (Prev)": "-", "Code": "TH18930", "Name": "เรชากรณ์ สุรีย์ชลพฤกษ์", "Birth Year": 2555, "Team": "มหาวิทยาลัยธนบุรี", "Age": 14, "NEW POINT JAN 26": 0.0, "Chonburi PAO 2026": 20.0, "Yasothon Open 2026": 0.0, "Total Point": 20.0}, {"Rank": 114, "Rank (Prev)": "-", "Code": "TH18793", "Name": "ปริตรต์ แดงจันทร์", "Birth Year": 2555, "Team": "สโมสร อิมพีเรียล เทเบิลเทนนิส", "Age": 14, "NEW POINT JAN 26": 0.0, "Chonburi PAO 2026": 20.0, "Yasothon Open 2026": 0.0, "Total Point": 20.0}, {"Rank": 114, "Rank (Prev)": "-", "Code": "TH20177", "Name": "จิตรกัณฐ์ สุดวิไล", "Birth Year": 2552, "Team": "-", "Age": 17, "NEW POINT JAN 26": 0.0, "Chonburi PAO 2026": 20.0, "Yasothon Open 2026": 0.0, "Total Point": 20.0}, {"Rank": 114, "Rank (Prev)": "-", "Code": "TH20180", "Name": "ธีรวัฒน์ คมฤทัย", "Birth Year": 2555, "Team": "โรงเรียนสาธิตจุฬาฯฝ่ายมัธยม", "Age": 14, "NEW POINT JAN 26": 0.0, "Chonburi PAO 2026": 20.0, "Yasothon Open 2026": 0.0, "Total Point": 20.0}, {"Rank": 114, "Rank (Prev)": "-", "Code": "TH20135", "Name": "พีชกร จันทบุตร", "Birth Year": 2554, "Team": "Spinning Star ", "Age": 15, "NEW POINT JAN 26": 0.0, "Chonburi PAO 2026": 20.0, "Yasothon Open 2026": 0.0, "Total Point": 20.0}, {"Rank": 114, "Rank (Prev)": "-", "Code": "TH19690", "Name": "ไพศาล สวรรค์", "Birth Year": 2555, "Team": "NLSCTTC2016", "Age": 14, "NEW POINT JAN 26": 0.0, "Chonburi PAO 2026": 20.0, "Yasothon Open 2026": 0.0, "Total Point": 20.0}, {"Rank": 114, "Rank (Prev)": "-", "Code": "TH20373", "Name": "กรธัช อินทรักษาทรัพย์", "Birth Year": 2555, "Team": "PINGPONG K-O TECH", "Age": 14, "NEW POINT JAN 26": 0.0, "Chonburi PAO 2026": 20.0, "Yasothon Open 2026": 0.0, "Total Point": 20.0}, {"Rank": 114, "Rank (Prev)": "-", "Code": "TH20185", "Name": "สรนันท์ แสงทอง", "Birth Year": 2555, "Team": "โรงเรียนสาธิตจุฬาฯฝ่ายมัธยม", "Age": 14, "NEW POINT JAN 26": 0.0, "Chonburi PAO 2026": 20.0, "Yasothon Open 2026": 0.0, "Total Point": 20.0}, {"Rank": 114, "Rank (Prev)": "-", "Code": "TH20209", "Name": "พงษพัฒน์ ศิริเกษ", "Birth Year": 2555, "Team": "โรงเรียนเทศบาลท่าโขลง1", "Age": 14, "NEW POINT JAN 26": 0.0, "Chonburi PAO 2026": 20.0, "Yasothon Open 2026": 0.0, "Total Point": 20.0}, {"Rank": 114, "Rank (Prev)": "-", "Code": "LA20218", "Name": "Mangkone Channavong", "Birth Year": 2555, "Team": "SISB", "Age": 14, "NEW POINT JAN 26": 0.0, "Chonburi PAO 2026": 20.0, "Yasothon Open 2026": 0.0, "Total Point": 20.0}, {"Rank": 114, "Rank (Prev)": "-", "Code": "TH20336", "Name": "พีมวิชญ์ ลอยกุลนันท์", "Birth Year": 2555, "Team": "โรงเรียนสาธิตจุฬาฯฝ่ายมัธยม", "Age": 14, "NEW POINT JAN 26": 0.0, "Chonburi PAO 2026": 20.0, "Yasothon Open 2026": 0.0, "Total Point": 20.0}, {"Rank": 114, "Rank (Prev)": "-", "Code": "TH18656", "Name": "ชินภัทร วิมานจันทร์", "Birth Year": 2555, "Team": "มหาวิทยาลัยธนบุรี", "Age": 14, "NEW POINT JAN 26": 0.0, "Chonburi PAO 2026": 20.0, "Yasothon Open 2026": 0.0, "Total Point": 20.0}, {"Rank": 114, "Rank (Prev)": "-", "Code": "TH20181", "Name": "ภัทร ธีรมงคลรัศมี", "Birth Year": 2555, "Team": "โรงเรียนสาธิตจุฬาฯฝ่ายมัธยม", "Age": 14, "NEW POINT JAN 26": 0.0, "Chonburi PAO 2026": 20.0, "Yasothon Open 2026": 0.0, "Total Point": 20.0}, {"Rank": 114, "Rank (Prev)": "-", "Code": "TH20388", "Name": "กมลวัฒน์ จิตมั่น", "Birth Year": 2555, "Team": "องค์การบริหารส่วนจังหวัดชลบุรี", "Age": 14, "NEW POINT JAN 26": 0.0, "Chonburi PAO 2026": 20.0, "Yasothon Open 2026": 0.0, "Total Point": 20.0}, {"Rank": 114, "Rank (Prev)": "-", "Code": "TH20242", "Name": "อนาวิน วังยายฉิม", "Birth Year": 2555, "Team": "โรงเรียนเทศบาลท่าโขลง1", "Age": 14, "NEW POINT JAN 26": 0.0, "Chonburi PAO 2026": 20.0, "Yasothon Open 2026": 0.0, "Total Point": 20.0}, {"Rank": 114, "Rank (Prev)": "-", "Code": "TH19873", "Name": "ธีร์ สินอุไรพันธ์", "Birth Year": 2555, "Team": "สโมสรเทเบิลเทนนิสบ้านปู", "Age": 14, "NEW POINT JAN 26": 0.0, "Chonburi PAO 2026": 20.0, "Yasothon Open 2026": 0.0, "Total Point": 20.0}, {"Rank": 114, "Rank (Prev)": "-", "Code": "TH20290", "Name": "พชรกฤษฏิ์ พร้อมจักรสิงห์", "Birth Year": 2553, "Team": "NLSCTTC2016", "Age": 16, "NEW POINT JAN 26": 0.0, "Chonburi PAO 2026": 20.0, "Yasothon Open 2026": 0.0, "Total Point": 20.0}, {"Rank": 114, "Rank (Prev)": "-", "Code": "TH18641", "Name": "ศารศีล องค์ชัยวัฒนะ", "Birth Year": 2555, "Team": "สโมสรกีฬาเซ็นทรัล", "Age": 14, "NEW POINT JAN 26": 0.0, "Chonburi PAO 2026": 20.0, "Yasothon Open 2026": 0.0, "Total Point": 20.0}, {"Rank": 114, "Rank (Prev)": "-", "Code": "TH18629", "Name": "ถิรวัฒน์ ชาญวิทย์วัฒนกิจ", "Birth Year": 2555, "Team": "สโมสรกีฬาเซ็นทรัล", "Age": 14, "NEW POINT JAN 26": 0.0, "Chonburi PAO 2026": 20.0, "Yasothon Open 2026": 0.0, "Total Point": 20.0}, {"Rank": 114, "Rank (Prev)": "-", "Code": "TH09963", "Name": "วนา อังกาบ", "Birth Year": 2555, "Team": "สโมสรกีฬาเซ็นทรัล", "Age": 14, "NEW POINT JAN 26": 0.0, "Chonburi PAO 2026": 20.0, "Yasothon Open 2026": 0.0, "Total Point": 20.0}, {"Rank": 114, "Rank (Prev)": "-", "Code": "TH20067", "Name": "พลกฤต แซ่หลี่", "Birth Year": 2555, "Team": "H.P.P. GYM", "Age": 14, "NEW POINT JAN 26": 0.0, "Chonburi PAO 2026": 20.0, "Yasothon Open 2026": 0.0, "Total Point": 20.0}, {"Rank": 114, "Rank (Prev)": "-", "Code": "TH19970", "Name": "เศวตฉัตร บังศรี", "Birth Year": 2555, "Team": "ปิงปองสปอร์ตชลบุรี", "Age": 14, "NEW POINT JAN 26": 0.0, "Chonburi PAO 2026": 20.0, "Yasothon Open 2026": 0.0, "Total Point": 20.0}, {"Rank": 114, "Rank (Prev)": "-", "Code": "TH20370", "Name": "ณัฐวัฒน์ แม้นนุสิทธิ์", "Birth Year": 2555, "Team": "องค์การบริหารส่วนจังหวัดชลบุรี", "Age": 14, "NEW POINT JAN 26": 0.0, "Chonburi PAO 2026": 20.0, "Yasothon Open 2026": 0.0, "Total Point": 20.0}, {"Rank": 114, "Rank (Prev)": "-", "Code": "TH19612", "Name": "ภูวเดช อัศวจุฬามณี", "Birth Year": 2555, "Team": "สโมสรเทเบิลเทนนิสบ้านปู", "Age": 14, "NEW POINT JAN 26": 0.0, "Chonburi PAO 2026": 20.0, "Yasothon Open 2026": 0.0, "Total Point": 20.0}, {"Rank": 114, "Rank (Prev)": "-", "Code": "TH18609", "Name": "พิชาภพ อนุตรวิโรจน์กุล", "Birth Year": 2555, "Team": "สโมสรกีฬาเซ็นทรัล", "Age": 14, "NEW POINT JAN 26": 0.0, "Chonburi PAO 2026": 20.0, "Yasothon Open 2026": 0.0, "Total Point": 20.0}, {"Rank": 114, "Rank (Prev)": "-", "Code": "TH20346", "Name": "วิทวัส ทองแตง", "Birth Year": 2555, "Team": "องค์การบริหารส่วนจังหวัดชลบุรี", "Age": 14, "NEW POINT JAN 26": 0.0, "Chonburi PAO 2026": 20.0, "Yasothon Open 2026": 0.0, "Total Point": 20.0}, {"Rank": 114, "Rank (Prev)": "-", "Code": "TH20073", "Name": "กันตพงศ์ คงเจริญโชค", "Birth Year": 2554, "Team": "-", "Age": 15, "NEW POINT JAN 26": 0.0, "Chonburi PAO 2026": 20.0, "Yasothon Open 2026": 0.0, "Total Point": 20.0}, {"Rank": 114, "Rank (Prev)": "-", "Code": "TH20109", "Name": "ณัฏฐ์ณยศ วงศ์เอกบุตร", "Birth Year": 2555, "Team": "-", "Age": 14, "NEW POINT JAN 26": 0.0, "Chonburi PAO 2026": 20.0, "Yasothon Open 2026": 0.0, "Total Point": 20.0}, {"Rank": 114, "Rank (Prev)": "-", "Code": "TH18827", "Name": "ภูกวิน มีศรี", "Birth Year": 2555, "Team": "สโมสร อิมพีเรียล เทเบิลเทนนิส", "Age": 14, "NEW POINT JAN 26": 0.0, "Chonburi PAO 2026": 20.0, "Yasothon Open 2026": 0.0, "Total Point": 20.0}, {"Rank": 114, "Rank (Prev)": "-", "Code": "TH19709", "Name": "กฤตยชญ์ ล้วนประพันธ์", "Birth Year": 2555, "Team": "NLSCTTC2016", "Age": 14, "NEW POINT JAN 26": 0.0, "Chonburi PAO 2026": 20.0, "Yasothon Open 2026": 0.0, "Total Point": 20.0}, {"Rank": 114, "Rank (Prev)": "-", "Code": "TH19185", "Name": "ภูริณัฐ พละศูนย์", "Birth Year": 2554, "Team": "มหาวิทยาลัยธนบุรี", "Age": 15, "NEW POINT JAN 26": 0.0, "Chonburi PAO 2026": 20.0, "Yasothon Open 2026": 0.0, "Total Point": 20.0}, {"Rank": 114, "Rank (Prev)": "-", "Code": "TH19585", "Name": "วัชรสิทธิ์ คงศักดิ์ศรีสกุล", "Birth Year": 2555, "Team": "ไทยรุ่ง", "Age": 14, "NEW POINT JAN 26": 0.0, "Chonburi PAO 2026": 20.0, "Yasothon Open 2026": 0.0, "Total Point": 20.0}, {"Rank": 114, "Rank (Prev)": "-", "Code": "TH20393", "Name": "พสุสิทธิ์ วรรณชมภู", "Birth Year": 2552, "Team": "-", "Age": 17, "NEW POINT JAN 26": 0.0, "Chonburi PAO 2026": 20.0, "Yasothon Open 2026": 0.0, "Total Point": 20.0}, {"Rank": 114, "Rank (Prev)": "-", "Code": "TH20212", "Name": "ศิลาชัย จั่นจินดา", "Birth Year": 2555, "Team": "โรงเรียนเทศบาลท่าโขลง1", "Age": 14, "NEW POINT JAN 26": 0.0, "Chonburi PAO 2026": 20.0, "Yasothon Open 2026": 0.0, "Total Point": 20.0}, {"Rank": 114, "Rank (Prev)": "-", "Code": "TH19367", "Name": "ชุติพนธ์ สนแก้ว", "Birth Year": 2555, "Team": "มหาวิทยาลัยธนบุรี", "Age": 14, "NEW POINT JAN 26": 0.0, "Chonburi PAO 2026": 20.0, "Yasothon Open 2026": 0.0, "Total Point": 20.0}, {"Rank": 115, "Rank (Prev)": 104, "Code": "NoCode 118", "Name": "โมไนย์ ศิริธัญญะรัตน์", "Birth Year": 2553, "Team": "SISB", "Age": 16, "NEW POINT JAN 26": 19.97, "Chonburi PAO 2026": 0.0, "Yasothon Open 2026": 0.0, "Total Point": 19.97}, {"Rank": 116, "Rank (Prev)": 105, "Code": "TH18552", "Name": "ยอดมนู โคตรบุปผา", "Birth Year": 2553, "Team": "มหาวิทยาลัยธนบุรี", "Age": 16, "NEW POINT JAN 26": 19.96, "Chonburi PAO 2026": 0.0, "Yasothon Open 2026": 0.0, "Total Point": 19.96}, {"Rank": 117, "Rank (Prev)": 106, "Code": "NoCode 120", "Name": "ชาญยุทธ พิณโท", "Birth Year": 2552, "Team": "เมืองทอง", "Age": 17, "NEW POINT JAN 26": 19.95, "Chonburi PAO 2026": 0.0, "Yasothon Open 2026": 0.0, "Total Point": 19.95}, {"Rank": 118, "Rank (Prev)": 107, "Code": "NoCode 121", "Name": "อถิพงษ์ ดาโสม", "Birth Year": 2552, "Team": "มกช.ชัยภูมิ", "Age": 17, "NEW POINT JAN 26": 19.0, "Chonburi PAO 2026": 0.0, "Yasothon Open 2026": 0.0, "Total Point": 19.0}, {"Rank": 119, "Rank (Prev)": 81, "Code": "TH20264", "Name": "ภูสิทธิ์ คงคารัตน์", "Birth Year": 2552, "Team": "Spinning Star", "Age": 17, "NEW POINT JAN 26": 38.12, "Chonburi PAO 2026": -20.0, "Yasothon Open 2026": 0.0, "Total Point": 18.12}, {"Rank": 120, "Rank (Prev)": 108, "Code": "NoCode 122", "Name": "รติพงศ์ โควิชาวิชกุล", "Birth Year": 2552, "Team": "ชมรมเทเบิลเทนนิสโรงเรียนนาหลวง", "Age": 17, "NEW POINT JAN 26": 16.7, "Chonburi PAO 2026": 0.0, "Yasothon Open 2026": 0.0, "Total Point": 16.7}, {"Rank": 121, "Rank (Prev)": 109, "Code": "NoCode 123", "Name": "วรินทร นวลศรี", "Birth Year": 2552, "Team": "สโมสรกีฬาเซ็นทรัล", "Age": 17, "NEW POINT JAN 26": 15.5, "Chonburi PAO 2026": 0.0, "Yasothon Open 2026": 0.0, "Total Point": 15.5}, {"Rank": 122, "Rank (Prev)": 110, "Code": "NoCode 124", "Name": "ติณณภพ ตุ้มปี่สุวรรณ​", "Birth Year": 2552, "Team": "เมืองทอง", "Age": 17, "NEW POINT JAN 26": 15.0, "Chonburi PAO 2026": 0.0, "Yasothon Open 2026": 0.0, "Total Point": 15.0}, {"Rank": 122, "Rank (Prev)": 110, "Code": "NoCode 125", "Name": "ปวริศ เหิรเมฆ", "Birth Year": 2553, "Team": "ปิงปองระยองคลับ", "Age": 16, "NEW POINT JAN 26": 15.0, "Chonburi PAO 2026": 0.0, "Yasothon Open 2026": 0.0, "Total Point": 15.0}, {"Rank": 122, "Rank (Prev)": 110, "Code": "NoCode 126", "Name": "พลพลัฏฐ์ สุริยะยรรยง", "Birth Year": 2552, "Team": "มหาวิทยาลัยธนบุรี", "Age": 17, "NEW POINT JAN 26": 15.0, "Chonburi PAO 2026": 0.0, "Yasothon Open 2026": 0.0, "Total Point": 15.0}, {"Rank": 122, "Rank (Prev)": 110, "Code": "NoCode 127", "Name": "มินย์ธาวี อิสาน", "Birth Year": 2552, "Team": "pingpong K-O tech", "Age": 17, "NEW POINT JAN 26": 15.0, "Chonburi PAO 2026": 0.0, "Yasothon Open 2026": 0.0, "Total Point": 15.0}, {"Rank": 122, "Rank (Prev)": 110, "Code": "NoCode 128", "Name": "ศุภกฤต พุ่มศิริ", "Birth Year": 2553, "Team": "BPP Table Tennis House", "Age": 16, "NEW POINT JAN 26": 15.0, "Chonburi PAO 2026": 0.0, "Yasothon Open 2026": 0.0, "Total Point": 15.0}, {"Rank": 123, "Rank (Prev)": 111, "Code": "NoCode 129", "Name": "เกษมสิษฐ์ เศรษฐาพัชร", "Birth Year": 2553, "Team": "Spinning Star", "Age": 16, "NEW POINT JAN 26": 14.99, "Chonburi PAO 2026": 0.0, "Yasothon Open 2026": 0.0, "Total Point": 14.99}, {"Rank": 124, "Rank (Prev)": 112, "Code": "NoCode 3", "Name": "พีระพัฒน์ ชนะหาญ", "Birth Year": 2553, "Team": "PPG 101", "Age": 16, "NEW POINT JAN 26": 14.98, "Chonburi PAO 2026": 0.0, "Yasothon Open 2026": 0.0, "Total Point": 14.98}, {"Rank": 125, "Rank (Prev)": 113, "Code": "NoCode 4", "Name": "อริศ คงศักดิ์ศรีสกุล", "Birth Year": 2553, "Team": "ไทยรุ่ง", "Age": 16, "NEW POINT JAN 26": 14.97, "Chonburi PAO 2026": 0.0, "Yasothon Open 2026": 0.0, "Total Point": 14.97}, {"Rank": 126, "Rank (Prev)": 114, "Code": "NoCode 5", "Name": "คีย์ตะวัน แก้วคำใต้", "Birth Year": 2553, "Team": "-", "Age": 16, "NEW POINT JAN 26": 14.96, "Chonburi PAO 2026": 0.0, "Yasothon Open 2026": 0.0, "Total Point": 14.96}, {"Rank": 127, "Rank (Prev)": 115, "Code": "NoCode 6", "Name": "รติวัฒน์ มูลเสนา", "Birth Year": 2552, "Team": "ชมรมเทเบิลเทนนิสโรงเรียนนาหลวง", "Age": 17, "NEW POINT JAN 26": 14.95, "Chonburi PAO 2026": 0.0, "Yasothon Open 2026": 0.0, "Total Point": 14.95}, {"Rank": 128, "Rank (Prev)": 116, "Code": "NoCode 7", "Name": "พชร ภิญโญรัตน์", "Birth Year": 2552, "Team": "KMITL", "Age": 17, "NEW POINT JAN 26": 12.5, "Chonburi PAO 2026": 0.0, "Yasothon Open 2026": 0.0, "Total Point": 12.5}, {"Rank": 129, "Rank (Prev)": 117, "Code": "NoCode 8", "Name": "กฤษณ์พีรัช​ รพี​วิมล​ศุภกร​", "Birth Year": 2552, "Team": "ชมรมเทเบิลเทนนิสช่องฟ้าซินเซิงวาณิชบำรุง", "Age": 17, "NEW POINT JAN 26": 10.5, "Chonburi PAO 2026": 0.0, "Yasothon Open 2026": 0.0, "Total Point": 10.5}, {"Rank": 129, "Rank (Prev)": 117, "Code": "NoCode 9", "Name": "อลงกต แต้สุวรรณ", "Birth Year": 2552, "Team": "NCN TABLE TENNIS", "Age": 17, "NEW POINT JAN 26": 10.5, "Chonburi PAO 2026": 0.0, "Yasothon Open 2026": 0.0, "Total Point": 10.5}, {"Rank": 130, "Rank (Prev)": 118, "Code": "NoCode 10", "Name": "FAN TING-CHANG", "Birth Year": 2554, "Team": "มหาวิทยาลัยธนบุรี", "Age": 15, "NEW POINT JAN 26": 10.0, "Chonburi PAO 2026": 0.0, "Yasothon Open 2026": 0.0, "Total Point": 10.0}, {"Rank": 130, "Rank (Prev)": 118, "Code": "NoCode 11", "Name": "KHANT PHONE THIT", "Birth Year": 2553, "Team": "Pin Academy", "Age": 16, "NEW POINT JAN 26": 10.0, "Chonburi PAO 2026": 0.0, "Yasothon Open 2026": 0.0, "Total Point": 10.0}, {"Rank": 130, "Rank (Prev)": 118, "Code": "NoCode 13", "Name": "YE YINT THU", "Birth Year": 2554, "Team": "Pin Academy", "Age": 15, "NEW POINT JAN 26": 10.0, "Chonburi PAO 2026": 0.0, "Yasothon Open 2026": 0.0, "Total Point": 10.0}, {"Rank": 130, "Rank (Prev)": 118, "Code": "NoCode 14", "Name": "คณิสศรณ์ พันธ์สกุล", "Birth Year": 2552, "Team": "-", "Age": 17, "NEW POINT JAN 26": 10.0, "Chonburi PAO 2026": 0.0, "Yasothon Open 2026": 0.0, "Total Point": 10.0}, {"Rank": 130, "Rank (Prev)": 118, "Code": "NoCode 15", "Name": "จิรัฏฐ์ ภัคจารุกิตติ์", "Birth Year": 2553, "Team": "สโมสรกีฬาเซ็นทรัล", "Age": 16, "NEW POINT JAN 26": 10.0, "Chonburi PAO 2026": 0.0, "Yasothon Open 2026": 0.0, "Total Point": 10.0}, {"Rank": 130, "Rank (Prev)": 118, "Code": "NoCode 16", "Name": "จิราธร เศรษฐไกรกุล", "Birth Year": 2554, "Team": "ชมรมเทเบิลเทนนิสช่องฟ้าซินเซิงวาณิชบำรุง", "Age": 15, "NEW POINT JAN 26": 10.0, "Chonburi PAO 2026": 0.0, "Yasothon Open 2026": 0.0, "Total Point": 10.0}, {"Rank": 130, "Rank (Prev)": 118, "Code": "NoCode 17", "Name": "ชยุต ห้วยเเก้ว", "Birth Year": 2552, "Team": "ปิงปองนครศรีธรรมราช", "Age": 17, "NEW POINT JAN 26": 10.0, "Chonburi PAO 2026": 0.0, "Yasothon Open 2026": 0.0, "Total Point": 10.0}, {"Rank": 130, "Rank (Prev)": 118, "Code": "NoCode 18", "Name": "ณธกร ​ข่วงอารินทร์", "Birth Year": 2554, "Team": "PATTAYA UNITED", "Age": 15, "NEW POINT JAN 26": 10.0, "Chonburi PAO 2026": 0.0, "Yasothon Open 2026": 0.0, "Total Point": 10.0}, {"Rank": 130, "Rank (Prev)": 118, "Code": "NoCode 19", "Name": "ณัฐภวินท์ อินชัยยงค์", "Birth Year": 2553, "Team": "pingpong K-O tech", "Age": 16, "NEW POINT JAN 26": 10.0, "Chonburi PAO 2026": 0.0, "Yasothon Open 2026": 0.0, "Total Point": 10.0}, {"Rank": 130, "Rank (Prev)": 118, "Code": "NoCode 20", "Name": "ถิรเมธ บวนภิรมย์", "Birth Year": 2552, "Team": "ชมรมเทเบิลเทนนิสจังหวัดตรัง", "Age": 17, "NEW POINT JAN 26": 10.0, "Chonburi PAO 2026": 0.0, "Yasothon Open 2026": 0.0, "Total Point": 10.0}, {"Rank": 130, "Rank (Prev)": 118, "Code": "NoCode 22", "Name": "ธนากร โพธิ์คำ", "Birth Year": 2553, "Team": "ชมรมเทเบิลเทนนิสโรงเรียนนาหลวง", "Age": 16, "NEW POINT JAN 26": 10.0, "Chonburi PAO 2026": 0.0, "Yasothon Open 2026": 0.0, "Total Point": 10.0}, {"Rank": 130, "Rank (Prev)": 118, "Code": "NoCode 23", "Name": "นิธิศ อินต๊ะ", "Birth Year": 2553, "Team": "Prospin Club", "Age": 16, "NEW POINT JAN 26": 10.0, "Chonburi PAO 2026": 0.0, "Yasothon Open 2026": 0.0, "Total Point": 10.0}, {"Rank": 130, "Rank (Prev)": 118, "Code": "NoCode 24", "Name": "บุณยภู อ่อนหวาน", "Birth Year": 2553, "Team": "ชมรมเทเบิลเทนนิสจังหวัดตรัง", "Age": 16, "NEW POINT JAN 26": 10.0, "Chonburi PAO 2026": 0.0, "Yasothon Open 2026": 0.0, "Total Point": 10.0}, {"Rank": 130, "Rank (Prev)": 118, "Code": "NoCode 25", "Name": "ปฐวี วิณวันก์", "Birth Year": 2552, "Team": "สโมสรเทเบิลเทนนิสตำรวจ", "Age": 17, "NEW POINT JAN 26": 10.0, "Chonburi PAO 2026": 0.0, "Yasothon Open 2026": 0.0, "Total Point": 10.0}, {"Rank": 130, "Rank (Prev)": 118, "Code": "NoCode 26", "Name": "ปิยวัฒน์ วรปัญญาสกุลชัย", "Birth Year": 2554, "Team": "Prospin Club", "Age": 15, "NEW POINT JAN 26": 10.0, "Chonburi PAO 2026": 0.0, "Yasothon Open 2026": 0.0, "Total Point": 10.0}, {"Rank": 130, "Rank (Prev)": 118, "Code": "NoCode 27", "Name": "พชรพล ตรีเดช", "Birth Year": 2552, "Team": "ชมรมเทเบิลเทนนิสโรงเรียนเทศบาล4(บ้านเชียงราย)", "Age": 17, "NEW POINT JAN 26": 10.0, "Chonburi PAO 2026": 0.0, "Yasothon Open 2026": 0.0, "Total Point": 10.0}, {"Rank": 130, "Rank (Prev)": 118, "Code": "NoCode 28", "Name": "พศิน ภักดีคีรีหยก", "Birth Year": 2553, "Team": "pingpong K-O tech", "Age": 16, "NEW POINT JAN 26": 10.0, "Chonburi PAO 2026": 0.0, "Yasothon Open 2026": 0.0, "Total Point": 10.0}, {"Rank": 130, "Rank (Prev)": 118, "Code": "NoCode 29", "Name": "พีรภัทร หงษ์เลิศกวิน", "Birth Year": 2552, "Team": "ห้างหุ้นส่วนจำกัด ซอฟต์แวร์ไทย", "Age": 17, "NEW POINT JAN 26": 10.0, "Chonburi PAO 2026": 0.0, "Yasothon Open 2026": 0.0, "Total Point": 10.0}, {"Rank": 130, "Rank (Prev)": 118, "Code": "NoCode 30", "Name": "ภัทรพงศ์ หมวดเอียด", "Birth Year": 2553, "Team": "ห้างหุ้นส่วนจำกัด ซอฟต์แวร์ไทย", "Age": 16, "NEW POINT JAN 26": 10.0, "Chonburi PAO 2026": 0.0, "Yasothon Open 2026": 0.0, "Total Point": 10.0}, {"Rank": 130, "Rank (Prev)": 118, "Code": "NoCode 31", "Name": "ภาคิน นันตะกูล", "Birth Year": 2552, "Team": "ชมรมเทเบิลเทนนิสโรงเรียนเทศบาล4(บ้านเชียงราย)", "Age": 17, "NEW POINT JAN 26": 10.0, "Chonburi PAO 2026": 0.0, "Yasothon Open 2026": 0.0, "Total Point": 10.0}, {"Rank": 130, "Rank (Prev)": 118, "Code": "NoCode 33", "Name": "เมธาสิทธิ์ นุ่นสังข์", "Birth Year": 2553, "Team": "โรงเรียนเทศบาลปลูกปัญญา ในพระอุปถัมภ์ฯ", "Age": 16, "NEW POINT JAN 26": 10.0, "Chonburi PAO 2026": 0.0, "Yasothon Open 2026": 0.0, "Total Point": 10.0}, {"Rank": 130, "Rank (Prev)": 118, "Code": "NoCode 34", "Name": "วุฒิพงษ์ เฉลิมเกียรติกวี", "Birth Year": 2552, "Team": "CS pingpong gym", "Age": 17, "NEW POINT JAN 26": 10.0, "Chonburi PAO 2026": 0.0, "Yasothon Open 2026": 0.0, "Total Point": 10.0}, {"Rank": 130, "Rank (Prev)": 118, "Code": "NoCode 35", "Name": "ศตวรรษ พสิษฐ์อัษฏายุธ", "Birth Year": 2552, "Team": "โรงเรียนเม็งรายมหาราชวิทยาคม", "Age": 17, "NEW POINT JAN 26": 10.0, "Chonburi PAO 2026": 0.0, "Yasothon Open 2026": 0.0, "Total Point": 10.0}, {"Rank": 130, "Rank (Prev)": 118, "Code": "NoCode 37", "Name": "สุวิจักขณ์ แก้วประเสริฐ", "Birth Year": 2553, "Team": "KTTA", "Age": 16, "NEW POINT JAN 26": 10.0, "Chonburi PAO 2026": 0.0, "Yasothon Open 2026": 0.0, "Total Point": 10.0}, {"Rank": 130, "Rank (Prev)": 118, "Code": "NoCode 38", "Name": "อนาวิน อิ่มอ่วม", "Birth Year": 2553, "Team": "Spinning Star", "Age": 16, "NEW POINT JAN 26": 10.0, "Chonburi PAO 2026": 0.0, "Yasothon Open 2026": 0.0, "Total Point": 10.0}, {"Rank": 130, "Rank (Prev)": 118, "Code": "NoCode 39", "Name": "อิทธิกร เทพเรียน", "Birth Year": 2553, "Team": "RIDER CHONBURI", "Age": 16, "NEW POINT JAN 26": 10.0, "Chonburi PAO 2026": 0.0, "Yasothon Open 2026": 0.0, "Total Point": 10.0}, {"Rank": 130, "Rank (Prev)": 118, "Code": "IN18818", "Name": "Tanmay Teli", "Birth Year": 2553, "Team": "สโมสรเทเบิลเทนนิสอิมพีเรียลสำโรง", "Age": 16, "NEW POINT JAN 26": 10.0, "Chonburi PAO 2026": 0.0, "Yasothon Open 2026": 0.0, "Total Point": 10.0}, {"Rank": 130, "Rank (Prev)": 118, "Code": "TH19594", "Name": "ศุภณัฐ ไชยนวรัตน์", "Birth Year": 2553, "Team": "ITC GLOBAL", "Age": 16, "NEW POINT JAN 26": 10.0, "Chonburi PAO 2026": 0.0, "Yasothon Open 2026": 0.0, "Total Point": 10.0}, {"Rank": 130, "Rank (Prev)": 118, "Code": "TH20131", "Name": "ธนเดช มานุวงษ์กุล", "Birth Year": 2554, "Team": "มหาวิทยาลัยธนบุรี", "Age": 15, "NEW POINT JAN 26": 10.0, "Chonburi PAO 2026": 0.0, "Yasothon Open 2026": 0.0, "Total Point": 10.0}, {"Rank": 131, "Rank (Prev)": 119, "Code": "NoCode 40", "Name": "ชนพล คำใจ", "Birth Year": 2552, "Team": "ยิมสามบาท เชียงใหม่", "Age": 17, "NEW POINT JAN 26": 7.82, "Chonburi PAO 2026": 0.0, "Yasothon Open 2026": 0.0, "Total Point": 7.82}, {"Rank": 132, "Rank (Prev)": 120, "Code": "NoCode 42", "Name": "วีรยุทธ ช้างขาว", "Birth Year": 2552, "Team": "ชมรมเทเบิลเทนนิสโรงเรียนนาหลวง", "Age": 17, "NEW POINT JAN 26": 7.58, "Chonburi PAO 2026": 0.0, "Yasothon Open 2026": 0.0, "Total Point": 7.58}, {"Rank": 133, "Rank (Prev)": 121, "Code": "NoCode 43", "Name": "เฉินซิง หลิว", "Birth Year": 2552, "Team": "รังเทพ", "Age": 17, "NEW POINT JAN 26": 7.5, "Chonburi PAO 2026": 0.0, "Yasothon Open 2026": 0.0, "Total Point": 7.5}, {"Rank": 134, "Rank (Prev)": 122, "Code": "NoCode 44", "Name": "RAYYAN ILHAN MOHD SHAFIQUL HADITHH", "Birth Year": 2553, "Team": "Sarang Table Tennis Academy", "Age": 16, "NEW POINT JAN 26": 6.6, "Chonburi PAO 2026": 0.0, "Yasothon Open 2026": 0.0, "Total Point": 6.6}, {"Rank": 135, "Rank (Prev)": 123, "Code": "NoCode 45", "Name": "CHANNAVONG HEUANGXAP", "Birth Year": 2553, "Team": "Dalavone Academy", "Age": 16, "NEW POINT JAN 26": 5.0, "Chonburi PAO 2026": 0.0, "Yasothon Open 2026": 0.0, "Total Point": 5.0}, {"Rank": 135, "Rank (Prev)": 123, "Code": "NoCode 46", "Name": "JASEM TALEB", "Birth Year": 2553, "Team": "Pin Academy", "Age": 16, "NEW POINT JAN 26": 5.0, "Chonburi PAO 2026": 0.0, "Yasothon Open 2026": 0.0, "Total Point": 5.0}, {"Rank": 135, "Rank (Prev)": 123, "Code": "NoCode 47", "Name": "Muhammad Danish Rayyan Razak", "Birth Year": 2552, "Team": "Sarang Table Tennis Academy", "Age": 17, "NEW POINT JAN 26": 5.0, "Chonburi PAO 2026": 0.0, "Yasothon Open 2026": 0.0, "Total Point": 5.0}, {"Rank": 135, "Rank (Prev)": 123, "Code": "NoCode 48", "Name": "ธนบดี แซ่ฉั่ว", "Birth Year": 2552, "Team": "Spinning Star", "Age": 17, "NEW POINT JAN 26": 5.0, "Chonburi PAO 2026": 0.0, "Yasothon Open 2026": 0.0, "Total Point": 5.0}, {"Rank": 135, "Rank (Prev)": 123, "Code": "NoCode 49", "Name": "ธราเทพ หงษ์ศาลา", "Birth Year": 2552, "Team": "สโมสรกีฬาเซ็นทรัล", "Age": 17, "NEW POINT JAN 26": 5.0, "Chonburi PAO 2026": 0.0, "Yasothon Open 2026": 0.0, "Total Point": 5.0}, {"Rank": 135, "Rank (Prev)": 123, "Code": "NoCode 50", "Name": "ปองคุณ เจนรุ่งโรจน์", "Birth Year": 2552, "Team": "Magic Pingpong", "Age": 17, "NEW POINT JAN 26": 5.0, "Chonburi PAO 2026": 0.0, "Yasothon Open 2026": 0.0, "Total Point": 5.0}, {"Rank": 135, "Rank (Prev)": 123, "Code": "NoCode 51", "Name": "รวีวัฒน์ สิมชมภู", "Birth Year": 2566, "Team": "วัฒนานคร", "Age": 3, "NEW POINT JAN 26": 5.0, "Chonburi PAO 2026": 0.0, "Yasothon Open 2026": 0.0, "Total Point": 5.0}, {"Rank": 136, "Rank (Prev)": 124, "Code": "NoCode 53", "Name": "นพเก้า จุลละโพธิ์", "Birth Year": 2552, "Team": "สโมสรกีฬาบีบีจี", "Age": 17, "NEW POINT JAN 26": 4.96, "Chonburi PAO 2026": 0.0, "Yasothon Open 2026": 0.0, "Total Point": 4.96}, {"Rank": 137, "Rank (Prev)": 125, "Code": "NoCode 54", "Name": "ธีรภัทร์ ศรีราม", "Birth Year": 2552, "Team": "ชมรมกีฬาเทเบิลเทนนิสจังหวัดนครศรีธรรมราช", "Age": 17, "NEW POINT JAN 26": 4.94, "Chonburi PAO 2026": 0.0, "Yasothon Open 2026": 0.0, "Total Point": 4.94}, {"Rank": 138, "Rank (Prev)": 126, "Code": "NoCode 55", "Name": "Zhen Xin Loo", "Birth Year": 2552, "Team": "ETTA", "Age": 17, "NEW POINT JAN 26": 4.93, "Chonburi PAO 2026": 0.0, "Yasothon Open 2026": 0.0, "Total Point": 4.93}, {"Rank": 139, "Rank (Prev)": 127, "Code": "NoCode 56", "Name": "โลมา อัมพร​พฤติ", "Birth Year": 2552, "Team": "-", "Age": 17, "NEW POINT JAN 26": 4.83, "Chonburi PAO 2026": 0.0, "Yasothon Open 2026": 0.0, "Total Point": 4.83}, {"Rank": 140, "Rank (Prev)": 128, "Code": "NoCode 57", "Name": "KEITH NG YU HIN -", "Birth Year": 2552, "Team": "Pin Academy", "Age": 17, "NEW POINT JAN 26": 2.5, "Chonburi PAO 2026": 0.0, "Yasothon Open 2026": 0.0, "Total Point": 2.5}]